{"name":"BST","tagline":"Bignetwork Software Team","body":"Du kan kontakta oss på: bignetworksoftwareteam snabela googlegroups punkt com\r\n\r\n# Projekt av BST:\r\n\r\n## BigNetwork.se\r\nFöreningens officiella hemsida. Avskalad för enkelhets skull. Ska byggas om från grunden men lagt på is på grund av låg prio.\r\n\r\n- [bignetwork.se](http://bignetwork.se)  \r\n\r\n## BAS/BHS?\r\nAchievementsystem, kommer snart. Existerande Achievementfunktioner finns i BLS.\r\n\r\n- [achievements.bignetwork.se](http://achievements.bignetwork.se)  \r\n\r\n### BBS (Bignetwork Bong System)\r\nKiosksystem (POS) som används för att sälja varor på våra evenemang.\r\n\r\n- [kiosk.wintergate.se](http://kiosk.wintergate.se)  \r\n- [kiosk.summergate.se](http://kiosk.summergate.se)  \r\n- [github.com/bignetwork/BBS](github.com/bignetwork/BBS)  \r\n\r\n## BIP (Bignetwork Internet Player)\r\nProjekt i skiss-stadiet. Ska tillåta användare att skapa YouTube och Spotify-spellistor och rösta upp låtar som ska spelas (på evenemang). Troligen en tu-delad lösning med ett webbgränssnitt för omröstning och en PC-applikation för att hantera uppspelning samt spellistor (för Spotify).\r\n\r\n## BLS (Bignetwork Lan System)\r\nDriver sidorna för WinterGate och SummerGate.\r\n\r\n- [wintergate.se](http://wintergate.se)\r\n- [summergate.se](http://summergate.se)\r\n\r\n## BUS (Bignetwork User System)\r\nExtraherat användarsystem från BLS.\r\n\r\n- [users.bignetwork.se](http://users.bignetwork.se)?\r\n\r\n## HighScores\r\nHämtar alla användare med deras AP och visar en highscorelista. Blir troligen en del av BAS/BHS senare.\r\n\r\n- [github.com/bignetwork/high-scores](http://github.com/bignetwork/high-scores)\r\n\r\n## LAN-portal\r\nListar LAN-partyn över landet.\r\n\r\n- [lanportal.heroku.com](http://lanportal.heroku.com)\r\n- [github.com/bignetwork/LAN-portal](http://github.com/bignetwork/LAN-portal)\r\n\r\n## LIVE\r\nBigscreenvisning av realtidsinfo fran olika system.\r\n\r\n- [github.com/bignetwork/Live](http://github.com/bignetwork/Live)\r\n\r\n## Lätt-MIPI\r\nAnpassning av realtidsomröstningssystemet mipi.se för visning på storbildsskärm.\r\n\r\n- [voting.heroku.com](http://voting.heroku.com)\r\n\r\n## MLS (Minigate Lan System)\r\nAnmälningssystem för mindre/enklare evenemang.\r\n\r\n- [minigate.bignetwork.se](http://minigate.bignetwork.se)\r\n\r\n## VPS (Virtuell Privat Server)\r\nEn server vi hyr hos Glesys. Används istället för ett webbhotell och för att driva våra sajter.\r\n\r\n- [94.247.168.234](http://94.247.168.234)","google":"","note":"Don't delete this file! It's used internally to help with page regeneration."}